poseidon_rules/__init__.py
poseidon_rules/errors.py
poseidon_rules/statement.py
poseidon_rules/test_statement.py
poseidon_rules/utils.py
poseidon_rules/validator.py
poseidon_rules-0.1.4.dist-info/METADATA
poseidon_rules-0.1.4.dist-info/WHEEL
poseidon_rules-0.1.4.dist-info/top_level.txt
poseidon_rules-0.1.4.dist-info/RECORD
